[
  {
    "model_type": "sigmoid",
    "mode_str": "Sigmoid",
    "seed": 42,
    "n_params": 418584,
    "best_val_loss": 1.6085869073867798,
    "total_time": 170.9516589641571,
    "history": [
      {
        "iter": 0,
        "train_loss": 4.206090927124023,
        "val_loss": 4.2038068771362305,
        "elapsed": 2.304110050201416
      },
      {
        "iter": 200,
        "train_loss": 2.3848254680633545,
        "val_loss": 2.396663188934326,
        "elapsed": 15.635611057281494
      },
      {
        "iter": 400,
        "train_loss": 2.131382942199707,
        "val_loss": 2.1667699813842773,
        "elapsed": 28.956265926361084
      },
      {
        "iter": 600,
        "train_loss": 1.9409867525100708,
        "val_loss": 2.0399675369262695,
        "elapsed": 42.141146183013916
      },
      {
        "iter": 800,
        "train_loss": 1.8026012182235718,
        "val_loss": 1.943998098373413,
        "elapsed": 54.94261407852173
      },
      {
        "iter": 1000,
        "train_loss": 1.7198296785354614,
        "val_loss": 1.8734959363937378,
        "elapsed": 67.76474595069885
      },
      {
        "iter": 1200,
        "train_loss": 1.6354343891143799,
        "val_loss": 1.8039222955703735,
        "elapsed": 81.02955794334412
      },
      {
        "iter": 1400,
        "train_loss": 1.5791640281677246,
        "val_loss": 1.7527672052383423,
        "elapsed": 93.49815011024475
      },
      {
        "iter": 1600,
        "train_loss": 1.538406252861023,
        "val_loss": 1.714890956878662,
        "elapsed": 106.19516897201538
      },
      {
        "iter": 1800,
        "train_loss": 1.5072916746139526,
        "val_loss": 1.6893867254257202,
        "elapsed": 118.93143200874329
      },
      {
        "iter": 2000,
        "train_loss": 1.4912933111190796,
        "val_loss": 1.6717654466629028,
        "elapsed": 129.25975108146667
      },
      {
        "iter": 2200,
        "train_loss": 1.4626752138137817,
        "val_loss": 1.6635888814926147,
        "elapsed": 137.51326513290405
      },
      {
        "iter": 2400,
        "train_loss": 1.448614239692688,
        "val_loss": 1.6451270580291748,
        "elapsed": 146.31314301490784
      },
      {
        "iter": 2600,
        "train_loss": 1.4364385604858398,
        "val_loss": 1.630306363105774,
        "elapsed": 154.44652104377747
      },
      {
        "iter": 2800,
        "train_loss": 1.425663948059082,
        "val_loss": 1.6085869073867798,
        "elapsed": 162.71235918998718
      },
      {
        "iter": 2999,
        "train_loss": 1.4051611423492432,
        "val_loss": 1.612634539604187,
        "elapsed": 170.94443202018738
      }
    ]
  },
  {
    "model_type": "sigmoid",
    "mode_str": "Sigmoid",
    "seed": 668,
    "n_params": 418584,
    "best_val_loss": 1.622703194618225,
    "total_time": 126.57181692123413,
    "history": [
      {
        "iter": 0,
        "train_loss": 4.177650451660156,
        "val_loss": 4.171215057373047,
        "elapsed": 1.2215008735656738
      },
      {
        "iter": 200,
        "train_loss": 2.3834831714630127,
        "val_loss": 2.391435146331787,
        "elapsed": 9.566425800323486
      },
      {
        "iter": 400,
        "train_loss": 2.1425223350524902,
        "val_loss": 2.187018632888794,
        "elapsed": 17.895121812820435
      },
      {
        "iter": 600,
        "train_loss": 1.9329216480255127,
        "val_loss": 2.020131826400757,
        "elapsed": 26.223958730697632
      },
      {
        "iter": 800,
        "train_loss": 1.7968257665634155,
        "val_loss": 1.949670433998108,
        "elapsed": 34.54350161552429
      },
      {
        "iter": 1000,
        "train_loss": 1.703352689743042,
        "val_loss": 1.8824992179870605,
        "elapsed": 42.836142778396606
      },
      {
        "iter": 1200,
        "train_loss": 1.6402792930603027,
        "val_loss": 1.809221625328064,
        "elapsed": 51.18695282936096
      },
      {
        "iter": 1400,
        "train_loss": 1.5855319499969482,
        "val_loss": 1.7766412496566772,
        "elapsed": 59.58067989349365
      },
      {
        "iter": 1600,
        "train_loss": 1.5452206134796143,
        "val_loss": 1.7372479438781738,
        "elapsed": 67.93147277832031
      },
      {
        "iter": 1800,
        "train_loss": 1.5147682428359985,
        "val_loss": 1.7076640129089355,
        "elapsed": 76.13931274414062
      },
      {
        "iter": 2000,
        "train_loss": 1.4899569749832153,
        "val_loss": 1.6995244026184082,
        "elapsed": 84.61203265190125
      },
      {
        "iter": 2200,
        "train_loss": 1.4741929769515991,
        "val_loss": 1.6770471334457397,
        "elapsed": 92.99601578712463
      },
      {
        "iter": 2400,
        "train_loss": 1.451810359954834,
        "val_loss": 1.6615002155303955,
        "elapsed": 101.42095994949341
      },
      {
        "iter": 2600,
        "train_loss": 1.4439282417297363,
        "val_loss": 1.6528749465942383,
        "elapsed": 109.75726985931396
      },
      {
        "iter": 2800,
        "train_loss": 1.4314059019088745,
        "val_loss": 1.6334717273712158,
        "elapsed": 118.17228674888611
      },
      {
        "iter": 2999,
        "train_loss": 1.4195841550827026,
        "val_loss": 1.622703194618225,
        "elapsed": 126.563729763031
      }
    ]
  },
  {
    "model_type": "sigmoid",
    "mode_str": "Sigmoid",
    "seed": 1337,
    "n_params": 418584,
    "best_val_loss": 1.615149974822998,
    "total_time": 97.6902060508728,
    "history": [
      {
        "iter": 0,
        "train_loss": 4.169268608093262,
        "val_loss": 4.165189743041992,
        "elapsed": 1.2593872547149658
      },
      {
        "iter": 200,
        "train_loss": 2.387336492538452,
        "val_loss": 2.4067740440368652,
        "elapsed": 9.666096210479736
      },
      {
        "iter": 400,
        "train_loss": 2.1291375160217285,
        "val_loss": 2.1859514713287354,
        "elapsed": 18.101950883865356
      },
      {
        "iter": 600,
        "train_loss": 1.9383971691131592,
        "val_loss": 2.0478339195251465,
        "elapsed": 26.516462087631226
      },
      {
        "iter": 800,
        "train_loss": 1.797910451889038,
        "val_loss": 1.9395908117294312,
        "elapsed": 35.00608205795288
      },
      {
        "iter": 1000,
        "train_loss": 1.6974029541015625,
        "val_loss": 1.8507286310195923,
        "elapsed": 44.08683800697327
      },
      {
        "iter": 1200,
        "train_loss": 1.627090573310852,
        "val_loss": 1.7951171398162842,
        "elapsed": 52.87281608581543
      },
      {
        "iter": 1400,
        "train_loss": 1.5736602544784546,
        "val_loss": 1.7565199136734009,
        "elapsed": 61.491170167922974
      },
      {
        "iter": 1600,
        "train_loss": 1.5354198217391968,
        "val_loss": 1.7293426990509033,
        "elapsed": 65.97580099105835
      },
      {
        "iter": 1800,
        "train_loss": 1.5020099878311157,
        "val_loss": 1.7017502784729004,
        "elapsed": 70.33126616477966
      },
      {
        "iter": 2000,
        "train_loss": 1.4869415760040283,
        "val_loss": 1.669958472251892,
        "elapsed": 74.75606608390808
      },
      {
        "iter": 2200,
        "train_loss": 1.4655508995056152,
        "val_loss": 1.6560659408569336,
        "elapsed": 79.23877906799316
      },
      {
        "iter": 2400,
        "train_loss": 1.4523502588272095,
        "val_loss": 1.635237693786621,
        "elapsed": 83.69657897949219
      },
      {
        "iter": 2600,
        "train_loss": 1.438676118850708,
        "val_loss": 1.6335293054580688,
        "elapsed": 88.14916706085205
      },
      {
        "iter": 2800,
        "train_loss": 1.4286898374557495,
        "val_loss": 1.615149974822998,
        "elapsed": 92.60065722465515
      },
      {
        "iter": 2999,
        "train_loss": 1.4166979789733887,
        "val_loss": 1.6275285482406616,
        "elapsed": 97.67479395866394
      }
    ]
  }
]